realtimex_toolkit/__init__.py
realtimex_toolkit/exceptions.py
realtimex_toolkit/py.typed
realtimex_toolkit/agent_flow/__init__.py
realtimex_toolkit/agent_skills/__init__.py
realtimex_toolkit/api/__init__.py
realtimex_toolkit/api/error_mapping.py
realtimex_toolkit/api/http_client.py
realtimex_toolkit/api/utils.py
realtimex_toolkit/credentials/__init__.py
realtimex_toolkit/credentials/manager.py
realtimex_toolkit/credentials/models.py
realtimex_toolkit/llm/__init__.py
realtimex_toolkit/llm/mappings.py
realtimex_toolkit/llm/providers.py
realtimex_toolkit/mcp/__init__.py
realtimex_toolkit/mcp/gmail.py
realtimex_toolkit/utils/__init__.py
realtimex_toolkit/utils/path_utils.py
realtimex_toolkit-1.6.0.dist-info/METADATA
realtimex_toolkit-1.6.0.dist-info/WHEEL
realtimex_toolkit-1.6.0.dist-info/RECORD
