Metadata-Version: 2.4
Name: realtimex_toolkit
Version: 1.6.0
Summary: Lightweight internal utilities for LLM provider configuration and credential management
Author: RealtimeX Team
License: Proprietary
Requires-Python: >=3.11
Requires-Dist: aiohttp>=3.9.0
Requires-Dist: cryptography==44.0.3
Requires-Dist: pydantic>=2.5.0
Requires-Dist: python-dotenv>=1.1.1
Requires-Dist: tenacity>=8.2.0
Provides-Extra: dev
Requires-Dist: mypy>=1.11.0; extra == 'dev'
Requires-Dist: pytest-asyncio>=0.23.0; extra == 'dev'
Requires-Dist: pytest-cov>=5.0.0; extra == 'dev'
Requires-Dist: pytest>=8.0.0; extra == 'dev'
Requires-Dist: ruff>=0.6.0; extra == 'dev'
